secretwallet/__init__.py
secretwallet/__main__.py
secretwallet/constants.py
secretwallet/main/__init__.py
secretwallet/main/configuration.py
secretwallet/main/myparser.py
secretwallet/session/__init__.py
secretwallet/session/client.py
secretwallet/session/service.py
secretwallet/storage/__init__.py
secretwallet/storage/aws_dynamo.py
secretwallet/storage/local_sqlite.py
secretwallet/storage/table.py
secretwallet/utils/__init__.py
secretwallet/utils/cryptutils.py
secretwallet/utils/dbutils.py
secretwallet/utils/fileutils.py
secretwallet/utils/ioutils.py
secretwallet/utils/logging.py
secretwallet/utils/password_manager.py
tests/__init__.py
tests/aws_config_test.py
tests/aws_dynamo_test.py
tests/cli_test.py
tests/cryptuils_test.py
tests/dbutils_test.py
tests/local_sqlite_test.py
tests/parameters_test.py
tests/password_test.py
tests/session_test.py
tests/data/test_integration.json
secret_wallet_codimoc-0.6.3.dist-info/LICENSE
secret_wallet_codimoc-0.6.3.dist-info/METADATA
secret_wallet_codimoc-0.6.3.dist-info/WHEEL
secret_wallet_codimoc-0.6.3.dist-info/entry_points.txt
secret_wallet_codimoc-0.6.3.dist-info/top_level.txt
secret_wallet_codimoc-0.6.3.dist-info/RECORD
