Metadata-Version: 2.1
Name: secret-wallet-codimoc
Version: 0.6.3
Summary: A cloud-based wallet for personal secrets
Home-page: https://github.com/codimoc/secret-wallet
Author: codimoc
Author-email: codimoc@prismoid.uk
Classifier: Programming Language :: Python :: 3
Classifier: License :: OSI Approved :: MIT License
Classifier: Operating System :: OS Independent
Requires-Python: >=3.6
License-File: LICENSE
Requires-Dist: boto3
Requires-Dist: cryptography
Requires-Dist: password-strength
Requires-Dist: python-daemon
Requires-Dist: docutils (<0.16)
Requires-Dist: pyreadline
